kme/__init__.py
kme/kme.py
kme-0.1.1.dist-info/LICENSE
kme-0.1.1.dist-info/METADATA
kme-0.1.1.dist-info/WHEEL
kme-0.1.1.dist-info/top_level.txt
kme-0.1.1.dist-info/RECORD
