Metadata-Version: 2.1
Name: kme
Version: 0.1.1
Summary: A library that enables building simple Kafka consumer/producer micro/nano services
Home-page: https://github.com/chrisjohnson00/kme
Author: Chris Johnson
Author-email: chrisjohnson00@hotmail.com
License: UNKNOWN
Project-URL: Bug Tracker, https://github.com/chrisjohnson00/kme/issues
Platform: UNKNOWN
Classifier: Programming Language :: Python :: 3
Classifier: License :: OSI Approved :: MIT License
Classifier: Operating System :: OS Independent
Requires-Python: >=3.6
License-File: LICENSE
Requires-Dist: jsonpickle (<3,>=2)
Requires-Dist: kafka-python (<3,>=2)
